sgnl_api/__init__.py
sgnl_api/decorators.py
sgnl_api/docs_api.py
sgnl_api/file.py
sgnl_api/scopes.py
sgnl_api/utils.py
sgnl_api-0.0.3.dist-info/LICENSE
sgnl_api-0.0.3.dist-info/METADATA
sgnl_api-0.0.3.dist-info/WHEEL
sgnl_api-0.0.3.dist-info/top_level.txt
sgnl_api-0.0.3.dist-info/RECORD
