Metadata-Version: 2.1
Name: sgnl-api
Version: 0.0.3
Summary: Asynchronous python wrapper over API sgnl.pro
Home-page: https://github.com/gritsyuk/sgnl-api
Download-URL: https://github.com/gritsyuk/sgnl-api/archive/refs/heads/develop.zip
Author: Igor Gritsyuk
Author-email: gritsyuk.igor@gmail.com
Project-URL: GitHub, https://github.com/gritsyuk/sgnl-api
Keywords: sgnl api signal docs construction supervision operation inspections constarctionsite building management
Classifier: Programming Language :: Python :: 3
Classifier: License :: OSI Approved :: MIT License
Classifier: Operating System :: OS Independent
Requires-Python: >=3.9
License-File: LICENSE
Requires-Dist: httpx >=0.27.2
Requires-Dist: aiofiles >=24.1.0
